multi_system_connector/__init__.py
multi_system_connector/azure_ai.py
multi_system_connector/cli.py
multi_system_connector/main.py
multi_system_connector/sharepoint.py
multi_system_connector/utils.py
multi_system_connector-0.1.1.dist-info/licenses/LICENSE
multi_system_connector-0.1.1.dist-info/METADATA
multi_system_connector-0.1.1.dist-info/WHEEL
multi_system_connector-0.1.1.dist-info/entry_points.txt
multi_system_connector-0.1.1.dist-info/top_level.txt
multi_system_connector-0.1.1.dist-info/RECORD
